deepsurveysim/.DS_Store
deepsurveysim/.pytest_cache/.gitignore
deepsurveysim/.pytest_cache/CACHEDIR.TAG
deepsurveysim/.pytest_cache/README.md
deepsurveysim/.pytest_cache/v/cache/nodeids
deepsurveysim/.pytest_cache/v/cache/stepwise
deepsurveysim/IO/.pytest_cache/.gitignore
deepsurveysim/IO/.pytest_cache/CACHEDIR.TAG
deepsurveysim/IO/.pytest_cache/README.md
deepsurveysim/IO/.pytest_cache/v/cache/nodeids
deepsurveysim/IO/.pytest_cache/v/cache/stepwise
deepsurveysim/IO/__init__.py
deepsurveysim/IO/read_config.py
deepsurveysim/IO/save_simulation.py
deepsurveysim/Survey/__init__.py
deepsurveysim/Survey/observation_variables.py
deepsurveysim/Survey/survey.py
deepsurveysim/Visuals/__init__.py
deepsurveysim/Visuals/position_plots.py
deepsurveysim/Visuals/reward_plots.py
deepsurveysim/__init__.py
deepsurveysim/settings/SEO.yaml
deepsurveysim/settings/equatorial_survey.yaml
deepsurveysim/settings/skybright_config.conf
deepsurveysim-0.1.0.dist-info/LICENSE
deepsurveysim-0.1.0.dist-info/WHEEL
deepsurveysim-0.1.0.dist-info/METADATA
deepsurveysim-0.1.0.dist-info/RECORD
