Metadata-Version: 2.1
Name: deepsurveysim
Version: 0.1.0
Summary: An astrological survey simulation designed for testing MDP-style algorithms
Home-page: https://github.com/deepskies/DeepSurveySim
License: BSD 3-Clause
Author: M. Voetberg
Author-email: maggiev@fnal.gov
Requires-Python: >=3.8,<4.0
Classifier: License :: Other/Proprietary License
Classifier: Programming Language :: Python :: 3
Classifier: Programming Language :: Python :: 3.8
Classifier: Programming Language :: Python :: 3.9
Classifier: Programming Language :: Python :: 3.10
Classifier: Programming Language :: Python :: 3.11
Requires-Dist: PyYAML (>=6.0,<7.0)
Requires-Dist: astroplan (>=0.8,<0.9)
Requires-Dist: configparser (>=5.3.0,<6.0.0)
Requires-Dist: numexpr (>=2.8.4,<3.0.0)
Requires-Dist: numpy (>=1.24.2,<2.0.0)
Requires-Dist: pandas (>=1.5.3,<2.0.0)
Project-URL: Documentation, https://deepsurveysim.readthedocs.io/en/latest/
Project-URL: Repository, https://github.com/deepskies/DeepSurveySim
